task/__init__.py
task/collect_framework.py
task/general_logic.py
collect_framework_oleksandr-0.0.1.dist-info/METADATA
collect_framework_oleksandr-0.0.1.dist-info/WHEEL
collect_framework_oleksandr-0.0.1.dist-info/entry_points.txt
collect_framework_oleksandr-0.0.1.dist-info/licenses/LICENSE
collect_framework_oleksandr-0.0.1.dist-info/RECORD
