Metadata-Version: 2.1
Name: collect_framework_oleksandr
Version: 0.0.1
Summary: Program count unique letters in a word
Project-URL: Homepage, https://git.foxminded.ua/foxstudent105474/task5
Author-email: Oleksandr Ponomarenko <trecc33@gmail.com>
License-File: LICENSE
Classifier: License :: OSI Approved :: GNU General Public License v3 (GPLv3)
Classifier: Operating System :: OS Independent
Classifier: Programming Language :: Python :: 3
Requires-Python: >=3.10
